[
  {
    "date": "2025-12-20",
    "kennelTags": [
      "bnh3"
    ],
    "title": "#263",
    "runNumber": 263,
    "startTime": "13:00",
    "hares": "MaBouche",
    "location": "Bar Delas Itanhaém",
    "latitude": -24.223121,
    "longitude": -46.904139
  },
  {
    "date": "2026-01-18",
    "kennelTags": [
      "bnh3"
    ],
    "title": "The Sunday r*n",
    "runNumber": 264,
    "startTime": "14:00",
    "hares": "MaBouche",
    "location": "Lanchonete Tom Cat, rua dos Jequitibás (or follow arrows from there), Jabaquara, Sāo Paulo.",
    "latitude": -23.646424535003597,
    "longitude": -46.64248022661902
  },
  {
    "date": "2026-02-21",
    "kennelTags": [
      "bnh3"
    ],
    "title": "The bloco trail",
    "runNumber": 265,
    "startTime": "13:00"
  },
  {
    "date": "2026-03-28",
    "kennelTags": [
      "bnh3"
    ],
    "title": "The t-shirt r*n",
    "runNumber": 266,
    "startTime": "14:00",
    "hares": "MaBouche",
    "location": "Rua Jandaia 20, Bela Vista, Sāo Paulo/SP",
    "latitude": -23.553555868143835,
    "longitude": -46.6377091625487
  },
  {
    "date": "2026-04-11",
    "kennelTags": [
      "bnh3"
    ],
    "title": "The Afterglow r*n",
    "runNumber": 266,
    "startTime": "14:00",
    "hares": "Pink Fluffer & Just Maria",
    "location": "SESC Pompeia, 93 rue Clelia, Sāo Paulo",
    "latitude": -23.5254094302667,
    "longitude": -46.68354353233422
  },
  {
    "date": "2026-06-06",
    "kennelTags": [
      "bnh3"
    ],
    "title": "Barbecue Hash",
    "runNumber": 267,
    "startTime": "11:00",
    "location": "Morumbi"
  }
]
